umatrix/__init__.py
umatrix/matrix.py
umatrix/__backend/__init__.py
umatrix/__backend/custom_exceptions_.py
umatrix-0.1.3.dist-info/LICENSE
umatrix-0.1.3.dist-info/METADATA
umatrix-0.1.3.dist-info/WHEEL
umatrix-0.1.3.dist-info/top_level.txt
umatrix-0.1.3.dist-info/RECORD
