Metadata-Version: 2.1
Name: umatrix
Version: 0.1.3
Summary: ''
Home-page: https://github.com/syedalimohsinbukhari/Matrices
Author: Syed Ali Mohsin Bukhari
Author-email: syedali.b@outlook.com
License: MIT
Classifier: License :: OSI Approved :: MIT License
Classifier: Programming Language :: Python :: 3.9
Classifier: Programming Language :: Python :: 3.10
Classifier: Programming Language :: Python :: 3.11
Requires-Python: >=3.9
License-File: LICENSE
Requires-Dist: setuptools
